{
   "data" : [
      {
         "Id" : "101",
         "Type" : "1",
         "Color" : "1"
      },
             {
             "Id" : "102",
             "Type" : "1",
             "Color" : "2"
             },
             {
             "Id" : "103",
             "Type" : "1",
             "Color" : "3"
             },
             {
             "Id" : "104",
             "Type" : "1",
             "Color" : "4"
             },
             {
             "Id" : "201",
             "Type" : "2",
             "Color" : "1"
             },
             {
             "Id" : "202",
             "Type" : "2",
             "Color" : "2"
             },
             {
             "Id" : "203",
             "Type" : "2",
             "Color" : "3"
             },
             {
             "Id" : "204",
             "Type" : "2",
             "Color" : "4"
             },
             {
             "Id" : "301",
             "Type" : "3",
             "Color" : "1"
             },
             {
             "Id" : "302",
             "Type" : "3",
             "Color" : "2"
             },
             {
             "Id" : "303",
             "Type" : "3",
             "Color" : "3"
             },
             {
             "Id" : "304",
             "Type" : "3",
             "Color" : "4"
             },
             {
             "Id" : "401",
             "Type" : "4",
             "Color" : "1"
             },
             {
             "Id" : "402",
             "Type" : "4",
             "Color" : "2"
             },
             {
             "Id" : "403",
             "Type" : "4",
             "Color" : "3"
             },
             {
             "Id" : "404",
             "Type" : "4",
             "Color" : "4"
             },
             {
             "Id" : "501",
             "Type" : "5",
             "Color" : "1"
             },
             {
             "Id" : "502",
             "Type" : "5",
             "Color" : "2"
             },
             {
             "Id" : "503",
             "Type" : "5",
             "Color" : "3"
             },
             {
             "Id" : "504",
             "Type" : "5",
             "Color" : "4"
             },
             {
             "Id" : "601",
             "Type" : "6",
             "Color" : "1"
             },
             {
             "Id" : "602",
             "Type" : "6",
             "Color" : "2"
             },
             {
             "Id" : "603",
             "Type" : "6",
             "Color" : "3"
             },
             {
             "Id" : "604",
             "Type" : "6",
             "Color" : "4"
             },
             {
             "Id" : "701",
             "Type" : "7",
             "Color" : "1"
             },
             {
             "Id" : "702",
             "Type" : "7",
             "Color" : "2"
             },
             {
             "Id" : "703",
             "Type" : "7",
             "Color" : "3"
             },
             {
             "Id" : "704",
             "Type" : "7",
             "Color" : "4"
             },
             {
             "Id" : "801",
             "Type" : "8",
             "Color" : "1"
             },
             {
             "Id" : "802",
             "Type" : "8",
             "Color" : "2"
             },
             {
             "Id" : "803",
             "Type" : "8",
             "Color" : "3"
             },
             {
             "Id" : "804",
             "Type" : "8",
             "Color" : "4"
             },
             {
             "Id" : "901",
             "Type" : "9",
             "Color" : "1"
             },
             {
             "Id" : "902",
             "Type" : "9",
             "Color" : "2"
             },
             {
             "Id" : "903",
             "Type" : "9",
             "Color" : "3"
             },
             {
             "Id" : "904",
             "Type" : "9",
             "Color" : "4"
             },
             {
             "Id" : "1001",
             "Type" : "10",
             "Color" : "1"
             },
             {
             "Id" : "1002",
             "Type" : "10",
             "Color" : "2"
             },
             {
             "Id" : "1003",
             "Type" : "10",
             "Color" : "3"
             },
             {
             "Id" : "1004",
             "Type" : "10",
             "Color" : "4"
             },
             {
             "Id" : "1101",
             "Type" : "11",
             "Color" : "1"
             },
             {
             "Id" : "1102",
             "Type" : "11",
             "Color" : "2"
             },
             {
             "Id" : "1103",
             "Type" : "11",
             "Color" : "3"
             },
             {
             "Id" : "1104",
             "Type" : "11",
             "Color" : "4"
             },
             {
             "Id" : "1201",
             "Type" : "12",
             "Color" : "1"
             },
             {
             "Id" : "1202",
             "Type" : "12",
             "Color" : "2"
             },
             {
             "Id" : "1203",
             "Type" : "12",
             "Color" : "3"
             },
             {
             "Id" : "1204",
             "Type" : "12",
             "Color" : "4"
             },
             {
             "Id" : "1301",
             "Type" : "13",
             "Color" : "1"
             },
             {
             "Id" : "1302",
             "Type" : "13",
             "Color" : "2"
             },
             {
             "Id" : "1303",
             "Type" : "13",
             "Color" : "3"
             },
             {
             "Id" : "1304",
             "Type" : "13",
             "Color" : "4"
             },
             {
             "Id" : "1404",
             "Type" : "14",
             "Color" : "4"
             },
             {
             "Id" : "1504",
             "Type" : "15",
             "Color" : "4"
             }
   ]
}
